[
      {
            "business_status":"OPERATIONAL",
            "geometry":{
                  "location":{
                        "lat":41.9685148,
                        "lng":-87.7208678
                  },
                  "viewport":{
                        "northeast":{
                              "lat":41.9697684303,
                              "lng":-87.7195201197
                        },
                        "southwest":{
                              "lat":41.9670704697,
                              "lng":-87.7222180803
                        }
                  }
            },
            "icon":"https:\/\/maps.gstatic.com\/mapfiles\/place_api\/icons\/v1\/png_71\/restaurant-71.png",
            "icon_background_color":"#FF9E67",
            "icon_mask_base_uri":"https:\/\/maps.gstatic.com\/mapfiles\/place_api\/icons\/v2\/restaurant_pinlet",
            "name":"Birrieria el Texcal",
            "opening_hours":{
                  "open_now":true
            },
            "photos":[
                  {
                        "height":2848,
                        "html_attributions":[
                              "<a href=\"https:\/\/maps.google.com\/maps\/contrib\/110837067543331486889\">Birrieria el Texcal<\/a>"
                        ],
                        "photo_reference":"Aap_uEDZ78AdYw152eCgjo3siggZ0vmdzaQw9Ogdp-JhW6YP_M_Nk10DxUl5SmVWh-TEIWDjt7T5n_d1YeRfePzfO1R68BJcPsrf4eGJ3NQK4StWJ9kmiF8d7r_C44SSf3PIDv3PIgb2uC7O3fa4hoOjEJu3r60wqniBYMvkRIvf70BFzODj",
                        "width":4288
                  }
            ],
            "place_id":"ChIJFQRB8vnND4gR0QE3MFSXN9c",
            "plus_code":{
                  "compound_code":"X79H+CM Chicago, IL, USA",
                  "global_code":"86HJX79H+CM"
            },
            "rating":4.3,
            "reference":"ChIJFQRB8vnND4gR0QE3MFSXN9c",
            "scope":"GOOGLE",
            "types":[
                  "restaurant",
                  "food",
                  "point_of_interest",
                  "establishment"
            ],
            "user_ratings_total":105,
            "vicinity":"3700 West Lawrence Avenue, Chicago",
            "price_level":null,
            "CBG":170311403011,
            "Radius":161.5790112137
      },
      {
            "business_status":"OPERATIONAL",
            "geometry":{
                  "location":{
                        "lat":41.9685226,
                        "lng":-87.7202921
                  },
                  "viewport":{
                        "northeast":{
                              "lat":41.9697749303,
                              "lng":-87.7189412697
                        },
                        "southwest":{
                              "lat":41.9670769697,
                              "lng":-87.7216392303
                        }
                  }
            },
            "icon":"https:\/\/maps.gstatic.com\/mapfiles\/place_api\/icons\/v1\/png_71\/restaurant-71.png",
            "icon_background_color":"#FF9E67",
            "icon_mask_base_uri":"https:\/\/maps.gstatic.com\/mapfiles\/place_api\/icons\/v2\/restaurant_pinlet",
            "name":"Tlayudas Oaxaca Grill",
            "opening_hours":{
                  "open_now":false
            },
            "photos":[
                  {
                        "height":4032,
                        "html_attributions":[
                              "<a href=\"https:\/\/maps.google.com\/maps\/contrib\/104609051762623015346\">Luis Alberto Bernal<\/a>"
                        ],
                        "photo_reference":"Aap_uEC4aWlVZUZD7s3Q-r4SmgfaCKYXGVkm3uIT8yoE7VvZlrIANy6gVJCVIZ9C06zzvbEgMWW5tNCZdupMU6tB8dJ371e7CRMxvJMUMxp7BpCP8kQGw0bPChwNWg6LfQKOtpRmqXZ34e3iT-KpeYCv7G5W275kWqZZoIk5gRdRi0rauJqa",
                        "width":3024
                  }
            ],
            "place_id":"ChIJXdtzzXTND4gRPtbpAbYbNqo",
            "plus_code":{
                  "compound_code":"X79H+CV Chicago, IL, USA",
                  "global_code":"86HJX79H+CV"
            },
            "rating":4.6,
            "reference":"ChIJXdtzzXTND4gRPtbpAbYbNqo",
            "scope":"GOOGLE",
            "types":[
                  "restaurant",
                  "food",
                  "point_of_interest",
                  "establishment"
            ],
            "user_ratings_total":72,
            "vicinity":"3652 West Lawrence Avenue, Chicago",
            "price_level":null,
            "CBG":170311403011,
            "Radius":161.5790112137
      },
      {
            "business_status":"OPERATIONAL",
            "geometry":{
                  "location":{
                        "lat":41.9684568,
                        "lng":-87.7205433
                  },
                  "viewport":{
                        "northeast":{
                              "lat":41.9697406803,
                              "lng":-87.7191930697
                        },
                        "southwest":{
                              "lat":41.9670427197,
                              "lng":-87.7218910303
                        }
                  }
            },
            "icon":"https:\/\/maps.gstatic.com\/mapfiles\/place_api\/icons\/v1\/png_71\/restaurant-71.png",
            "icon_background_color":"#FF9E67",
            "icon_mask_base_uri":"https:\/\/maps.gstatic.com\/mapfiles\/place_api\/icons\/v2\/restaurant_pinlet",
            "name":"Thiago's Restaurant Mexican-American Food",
            "opening_hours":{
                  "open_now":false
            },
            "photos":[
                  {
                        "height":3024,
                        "html_attributions":[
                              "<a href=\"https:\/\/maps.google.com\/maps\/contrib\/117194202909720767722\">SONIDO PRINCIPE MAYA<\/a>"
                        ],
                        "photo_reference":"Aap_uEBboyDTfB1H4ns7PCUFMajwxhY_KhYGw3RDfTeRUjY2r4Cv_y-QJTUMVMHc9QisaqQswdN6ddUewBZ_KY8NrJUjxHx2Y7ek_Vee9y_ZAybFU0c0wRb8kHcPVoyeSywMcTEpAJA1dkUOIcpBdW-dwnsFXQozPski1_G6zfq-Ltu-hU9L",
                        "width":4032
                  }
            ],
            "place_id":"ChIJhxLX3yDND4gRN3qzAcpfDxA",
            "plus_code":{
                  "compound_code":"X79H+9Q Chicago, IL, USA",
                  "global_code":"86HJX79H+9Q"
            },
            "rating":5.0,
            "reference":"ChIJhxLX3yDND4gRN3qzAcpfDxA",
            "scope":"GOOGLE",
            "types":[
                  "restaurant",
                  "food",
                  "point_of_interest",
                  "establishment"
            ],
            "user_ratings_total":38,
            "vicinity":"3658 West Lawrence Avenue, Chicago",
            "price_level":null,
            "CBG":170311403011,
            "Radius":161.5790112137
      },
      {
            "business_status":"OPERATIONAL",
            "geometry":{
                  "location":{
                        "lat":41.9684313,
                        "lng":-87.7209068
                  },
                  "viewport":{
                        "northeast":{
                              "lat":41.9697266303,
                              "lng":-87.7195396197
                        },
                        "southwest":{
                              "lat":41.9670286697,
                              "lng":-87.7222375803
                        }
                  }
            },
            "icon":"https:\/\/maps.gstatic.com\/mapfiles\/place_api\/icons\/v1\/png_71\/restaurant-71.png",
            "icon_background_color":"#FF9E67",
            "icon_mask_base_uri":"https:\/\/maps.gstatic.com\/mapfiles\/place_api\/icons\/v2\/restaurant_pinlet",
            "name":"El Poblano Restaurant Bar",
            "opening_hours":{
                  "open_now":false
            },
            "photos":[
                  {
                        "height":2688,
                        "html_attributions":[
                              "<a href=\"https:\/\/maps.google.com\/maps\/contrib\/112254516786155557225\">Eman<\/a>"
                        ],
                        "photo_reference":"Aap_uEC8CgIN-gUwmla5Rtp_jLxVdOvNxDSLjTtYoPq3Ils51C8ge-xzSZnYvdtAo93k64ZOGPALahbTAbIm9gPigrpa-XyQR9D7jEfOOAAG1TdGWSfLFNE7N59XAuw6kETHzBPQdMuO2dyaZy05JtP_EHqC6GsKD5HoLSFhatwQ0fg9802J",
                        "width":1475
                  }
            ],
            "place_id":"ChIJv26W8tzND4gRn7jkLx_hMuo",
            "plus_code":{
                  "compound_code":"X79H+9J Chicago, IL, USA",
                  "global_code":"86HJX79H+9J"
            },
            "rating":5.0,
            "reference":"ChIJv26W8tzND4gRn7jkLx_hMuo",
            "scope":"GOOGLE",
            "types":[
                  "restaurant",
                  "food",
                  "point_of_interest",
                  "establishment"
            ],
            "user_ratings_total":1,
            "vicinity":"Chicago",
            "price_level":null,
            "CBG":170311403011,
            "Radius":161.5790112137
      },
      {
            "business_status":"OPERATIONAL",
            "geometry":{
                  "location":{
                        "lat":41.9685238,
                        "lng":-87.7213903
                  },
                  "viewport":{
                        "northeast":{
                              "lat":41.9697717303,
                              "lng":-87.7200420697
                        },
                        "southwest":{
                              "lat":41.9670737697,
                              "lng":-87.7227400303
                        }
                  }
            },
            "icon":"https:\/\/maps.gstatic.com\/mapfiles\/place_api\/icons\/v1\/png_71\/restaurant-71.png",
            "icon_background_color":"#FF9E67",
            "icon_mask_base_uri":"https:\/\/maps.gstatic.com\/mapfiles\/place_api\/icons\/v2\/restaurant_pinlet",
            "name":"El Gallo Bravo S. N .\ud83c\udfe0",
            "opening_hours":{
                  "open_now":true
            },
            "photos":[
                  {
                        "height":2560,
                        "html_attributions":[
                              "<a href=\"https:\/\/maps.google.com\/maps\/contrib\/114197585390693773507\">El Gallo Bravo S. N .\ud83c\udfe0<\/a>"
                        ],
                        "photo_reference":"Aap_uEDkESoihTCNS1nIFy9QCA5-XuctHIEAY5xLyzWUGgVV7CxIeCkIw-DtI1DNGnwdAJJh4m3PD7mwgwakO8UHN3VGtclxI6G4NFfJMakWVD8EqZTR0MUqn3YojUcqDyKtgKm6e44I-1IQ2yjNXFvGNwoLUTAmqUrP60OK-JNzLLaXXWb5",
                        "width":1440
                  }
            ],
            "place_id":"ChIJC3cvjtzND4gRMDZwm4Vk5a4",
            "plus_code":{
                  "compound_code":"X79H+CC Chicago, IL, USA",
                  "global_code":"86HJX79H+CC"
            },
            "rating":4.0,
            "reference":"ChIJC3cvjtzND4gRMDZwm4Vk5a4",
            "scope":"GOOGLE",
            "types":[
                  "restaurant",
                  "food",
                  "point_of_interest",
                  "establishment"
            ],
            "user_ratings_total":517,
            "vicinity":"3714 West Lawrence Avenue, Chicago",
            "price_level":1.0,
            "CBG":170311403011,
            "Radius":161.5790112137
      },
      {
            "business_status":"OPERATIONAL",
            "geometry":{
                  "location":{
                        "lat":41.9682053,
                        "lng":-87.7200279
                  },
                  "viewport":{
                        "northeast":{
                              "lat":41.9696176803,
                              "lng":-87.7186801697
                        },
                        "southwest":{
                              "lat":41.9669197197,
                              "lng":-87.7213781303
                        }
                  }
            },
            "icon":"https:\/\/maps.gstatic.com\/mapfiles\/place_api\/icons\/v1\/png_71\/restaurant-71.png",
            "icon_background_color":"#FF9E67",
            "icon_mask_base_uri":"https:\/\/maps.gstatic.com\/mapfiles\/place_api\/icons\/v2\/restaurant_pinlet",
            "name":"La Piramide",
            "opening_hours":{
                  "open_now":true
            },
            "photos":[
                  {
                        "height":1857,
                        "html_attributions":[
                              "<a href=\"https:\/\/maps.google.com\/maps\/contrib\/109669855484647094723\">David Johnsen<\/a>"
                        ],
                        "photo_reference":"Aap_uEBOzXys_lIKLK27pb3prxMV2Rku00ZzPxMoFP-dcwd16L9R1d85UR9W139sQnSg7si1FYjjucjwI7bsEHiRiqVWPzYIe-_nZY6oyWpHpuJYtuofGhnN3i6NtiGq53y_JG4I731jH2Ui7uJTZ016Ke89Wu_GM_GQf43OHRDCJ2zSgYH4",
                        "width":3070
                  }
            ],
            "place_id":"ChIJxRP549zND4gRW1L9-IvzR-w",
            "plus_code":{
                  "compound_code":"X79H+7X Chicago, IL, USA",
                  "global_code":"86HJX79H+7X"
            },
            "rating":4.5,
            "reference":"ChIJxRP549zND4gRW1L9-IvzR-w",
            "scope":"GOOGLE",
            "types":[
                  "restaurant",
                  "food",
                  "point_of_interest",
                  "establishment"
            ],
            "user_ratings_total":59,
            "vicinity":"3645 West Lawrence Avenue, Chicago",
            "price_level":null,
            "CBG":170311403011,
            "Radius":161.5790112137
      },
      {
            "business_status":"OPERATIONAL",
            "geometry":{
                  "location":{
                        "lat":41.9686038,
                        "lng":-87.7192468
                  },
                  "viewport":{
                        "northeast":{
                              "lat":41.9698217803,
                              "lng":-87.7178908697
                        },
                        "southwest":{
                              "lat":41.9671238197,
                              "lng":-87.7205888303
                        }
                  }
            },
            "icon":"https:\/\/maps.gstatic.com\/mapfiles\/place_api\/icons\/v1\/png_71\/restaurant-71.png",
            "icon_background_color":"#FF9E67",
            "icon_mask_base_uri":"https:\/\/maps.gstatic.com\/mapfiles\/place_api\/icons\/v2\/restaurant_pinlet",
            "name":"Ovidio Vargas",
            "opening_hours":{
                  "open_now":false
            },
            "photos":[
                  {
                        "height":4032,
                        "html_attributions":[
                              "<a href=\"https:\/\/maps.google.com\/maps\/contrib\/115462807482404443263\">Willy Castillo<\/a>"
                        ],
                        "photo_reference":"Aap_uEATbG_LV66q-_CDsqoJrPiNLSYhCCbmHXqdecNy2PUXqT3H8-hxeC-QmZxvFdX8elPiviIjmzYHuaRaWgYfL7JkasRKXLe-RaB2dU2oE_MJKNF9VXr3Q4FNUUB7mBGkFZoFi49uWfN-iR8qiTSPitB7ec8D72ulGL7h2fG_r4VUaaP8",
                        "width":3024
                  }
            ],
            "place_id":"ChIJU7LmBN3ND4gR3dJw0Q20Zos",
            "plus_code":{
                  "compound_code":"X79J+C8 Chicago, IL, USA",
                  "global_code":"86HJX79J+C8"
            },
            "rating":2.5,
            "reference":"ChIJU7LmBN3ND4gR3dJw0Q20Zos",
            "scope":"GOOGLE",
            "types":[
                  "restaurant",
                  "food",
                  "point_of_interest",
                  "establishment"
            ],
            "user_ratings_total":2,
            "vicinity":"3626 West Lawrence Avenue, Chicago",
            "price_level":null,
            "CBG":170311403011,
            "Radius":161.5790112137
      },
      {
            "business_status":"OPERATIONAL",
            "geometry":{
                  "location":{
                        "lat":41.9684378,
                        "lng":-87.7193246
                  },
                  "viewport":{
                        "northeast":{
                              "lat":41.9697387803,
                              "lng":-87.7179297697
                        },
                        "southwest":{
                              "lat":41.9670408197,
                              "lng":-87.7206277303
                        }
                  }
            },
            "icon":"https:\/\/maps.gstatic.com\/mapfiles\/place_api\/icons\/v1\/png_71\/restaurant-71.png",
            "icon_background_color":"#FF9E67",
            "icon_mask_base_uri":"https:\/\/maps.gstatic.com\/mapfiles\/place_api\/icons\/v2\/restaurant_pinlet",
            "name":"Taqueria Y Cafeteria Siglo XX",
            "opening_hours":{
                  "open_now":false
            },
            "photos":[
                  {
                        "height":2656,
                        "html_attributions":[
                              "<a href=\"https:\/\/maps.google.com\/maps\/contrib\/109669855484647094723\">David Johnsen<\/a>"
                        ],
                        "photo_reference":"Aap_uECBq1NACarLcFZZQn9af1xhOqPDitDIoEngEL3c6RqMRhb_XwrAv0UXZ-TYcLTxa7BHZ34F251UC_JFoItpAjcBv_mad5TITbOUbekyt50xnuxcSnCRnGO2nUZiJT63hRWyRrq_ch7WgzXIqYB4tVZVfn46bTBBCbxKwlwrTh2ZflyD",
                        "width":3868
                  }
            ],
            "place_id":"ChIJeeHLHN3ND4gRCmZiXB9NpBc",
            "plus_code":{
                  "compound_code":"X79J+97 Chicago, IL, USA",
                  "global_code":"86HJX79J+97"
            },
            "rating":4.3,
            "reference":"ChIJeeHLHN3ND4gRCmZiXB9NpBc",
            "scope":"GOOGLE",
            "types":[
                  "restaurant",
                  "food",
                  "point_of_interest",
                  "establishment"
            ],
            "user_ratings_total":65,
            "vicinity":"3626 West Lawrence Avenue, Chicago",
            "price_level":null,
            "CBG":170311403011,
            "Radius":161.5790112137
      }
]